Workbook

Sheet Instructions
B2: 📊 Cash Flow Command Center
B4: Welcome to your premium financial planning tool from Charge Wealth!
B6: 🎯 Overview
B7: • This Cash Flow Command Center helps you track every dollar coming in and going out.
B8: • Use the Dashboard for a quick financial snapshot, and detailed sheets for tracking.
B9: • All calculations update automatically as you enter data.
B11: 📝 Getting Started
B12: • Start with the 'Income' sheet - enter all your income sources
B13: • Move to 'Fixed Expenses' for recurring monthly bills
B14: • Use 'Variable Expenses' for discretionary spending
B15: • The Dashboard will automatically calculate your cash flow position
B17: 💡 Pro Tips
... B29: Questions? Visit chargewealth.co for support and more premium tools.

Sheet Dashboard
B2: Cash Flow Command Center
B3: Your Complete Financial Picture
B4: Powered by Charge Wealth
B6: KEY METRICS
B8: Monthly Income | C8: =Income!H15
B9: Monthly Expenses | C9: ='Fixed Expenses'!E20+'Variable Expenses'!E25
B10: Net Cash Flow | C10: =B9-B10
B11: Savings Rate | C11: =IF(B9>0,B11/B9,0)
B12: Emergency Runway | C12: =IF(B10>0,Settings!B5/B10,0)
B16: 12-MONTH CASH FLOW PROJECTION
B18: Category | C18: Jan | D18: Feb | E18: Mar | F18: Apr | G18: May | H18: Jun | I18: Jul | J18: Aug | K18: Sep | L18: Oct | M18: Nov | N18: Dec
B19: Projected Income | C19: =$C$9*(1+Settings!$B$7)^0 | D19: =$C$9*(1+Settings!$B$7)^1 | E19: =$C$9*(1+Settings!$B$7)^2 | F19: =$C$9*(1+Settings!$B$7)^3 | G19: =$C$9*(1+Settings!$B$7)^4 | H19: =$C$9*(1+Settings!$B$7)^5 | I19: =$C$9*(1+Settings!$B$7)^6 | J19: =$C$9*(1+Settings!$B$7)^7 | K19: =$C$9*(1+Settings!$B$7)^8 | L19: =$C$9*(1+Settings!$B$7)^9 | M19: =$C$9*(1+Settings!$B$7)^10 | N19: =$C$9*(1+Settings!$B$7)^11
B20: Projected Expenses | C20: =$C$10*(1+Settings!$B$8)^0 | D20: =$C$10*(1+Settings!$B$8)^1 | E20: =$C$10*(1+Settings!$B$8)^2 | F20: =$C$10*(1+Settings!$B$8)^3 | G20: =$C$10*(1+Settings!$B$8)^4 | H20: =$C$10*(1+Settings!$B$8)^5 | I20: =$C$10*(1+Settings!$B$8)^6 | J20: =$C$10*(1+Settings!$B$8)^7 | K20: =$C$10*(1+Settings!$B$8)^8 | L20: =$C$10*(1+Settings!$B$8)^9 | M20: =$C$10*(1+Settings!$B$8)^10 | N20: =$C$10*(1+Settings!$B$8)^11
B21: Net Cash Flow | C21: =C19-C20 | D21: =D19-D20 | E21: =E19-E20 | F21: =F19-F20 | G21: =G19-G20 | H21: =H19-H20 | I21: =I19-I20 | J21: =J19-J20 | ... N21: =N19-N20
B22: Cumulative Balance | C22: =Settings!$B$5+C21 | D22: =C22+D21 | E22: =D22+E21 | F22: =E22+F21 | G22: =F22+G21 | H22: =G22+H21 | I22: =H22+I21 | J22: =I22+J21 | K22: =J22+K21 | ... N22: =M22+N21

Sheet Income
B2: Income Tracking
B3: All Revenue Sources
B4: Powered by Charge Wealth
B6: Source | C6: Type | D6: Frequency | E6: Amount | F6: Annual Total | G6: Monthly Equiv. | H6: Notes
B7: Primary Salary | C7: W-2 | D7: Bi-weekly | E7: 3500 | F7: =IF(D7="Weekly",E7*52,IF(D7="Bi-weekly",E7*26,IF(D7="Monthly",E7*12,IF(D7="Quarterly",E7*4,E7)))) | G7: =F7/12
B8: Side Business | C8: 1099 | D8: Monthly | E8: 1200 | F8: =IF(D8="Weekly",E8*52,IF(D8="Bi-weekly",E8*26,IF(D8="Monthly",E8*12,IF(D8="Quarterly",E8*4,E8)))) | G8: =F8/12
B9: Dividends | C9: Investment | D9: Quarterly | E9: 500 | F9: =IF(D9="Weekly",E9*52,IF(D9="Bi-weekly",E9*26,IF(D9="Monthly",E9*12,IF(D9="Quarterly",E9*4,E9)))) | G9: =F9/12
B10: Rental Income | C10: Passive | D10: Monthly | E10: 1800 | F10: =IF(D10="Weekly",E10*52,IF(D10="Bi-weekly",E10*26,IF(D10="Monthly",E10*12,IF(D10="Quarterly",E10*4,E10)))) | G10: =F10/12
B11: Freelance | C11: 1099 | D11: Variable | E11: 800 | F11: =IF(D11="Weekly",E11*52,IF(D11="Bi-weekly",E11*26,IF(D11="Monthly",E11*12,IF(D11="Quarterly",E11*4,E11)))) | G11: =F11/12
F12: =IF(D12="Weekly",E12*52,IF(D12="Bi-weekly",E12*26,IF(D12="Monthly",E12*12,IF(D12="Quarterly",E12*4,E12)))) | G12: =F12/12
F13: =IF(D13="Weekly",E13*52,IF(D13="Bi-weekly",E13*26,IF(D13="Monthly",E13*12,IF(D13="Quarterly",E13*4,E13)))) | G13: =F13/12
F14: =IF(D14="Weekly",E14*52,IF(D14="Bi-weekly",E14*26,IF(D14="Monthly",E14*12,IF(D14="Quarterly",E14*4,E14)))) | G14: =F14/12
F15: =IF(D15="Weekly",E15*52,IF(D15="Bi-weekly",E15*26,IF(D15="Monthly",E15*12,IF(D15="Quarterly",E15*4,E15)))) | G15: =F15/12 | H15: =G18
F16: =IF(D16="Weekly",E16*52,IF(D16="Bi-weekly",E16*26,IF(D16="Monthly",E16*12,IF(D16="Quarterly",E16*4,E16)))) | G16: =F16/12
B18: TOTAL | F18: =SUM(F7:F16) | G18: =SUM(G7:G16)

Sheet Fixed Expenses
B2: Fixed Expenses
B3: Recurring Monthly Bills
B4: Powered by Charge Wealth
B6: Expense | C6: Category | D6: Due Date | E6: Amount | F6: Annual Total
B7: Rent/Mortgage | C7: Housing | D7: 1 | E7: 2200 | F7: =E7*12
B8: Car Payment | C8: Transportation | D8: 15 | E8: 450 | F8: =E8*12
B9: Car Insurance | C9: Insurance | D9: 5 | E9: 125 | F9: =E9*12
B10: Health Insurance | C10: Insurance | D10: 1 | E10: 350 | F10: =E10*12
B11: Phone | C11: Utilities | D11: 20 | E11: 85 | F11: =E11*12
B12: Internet | C12: Utilities | D12: 12 | E12: 75 | F12: =E12*12
B13: Streaming Services | C13: Entertainment | D13: 1 | E13: 45 | F13: =E13*12
B14: Gym Membership | C14: Health | D14: 1 | E14: 50 | F14: =E14*12
F15: =E15*12
F16: =E16*12
F17: =E17*12
F18: =E18*12
F19: =E19*12
E20: =E21
B21: TOTAL | E21: =SUM(E7:E19)

Sheet Variable Expenses
B2: Variable Expenses
B3: Discretionary Spending
B4: Powered by Charge Wealth
B6: Category | C6: Budget | D6: Actual | E6: Variance | F6: % of Budget
B7: Groceries | C7: 600 | D7: 580 | E7: =C7-D7 | F7: =IF(C7>0,D7/C7,0)
B8: Dining Out | C8: 300 | D8: 420 | E8: =C8-D8 | F8: =IF(C8>0,D8/C8,0)
B9: Gas/Transportation | C9: 200 | D9: 175 | E9: =C9-D9 | F9: =IF(C9>0,D9/C9,0)
B10: Shopping | C10: 200 | D10: 310 | E10: =C10-D10 | F10: =IF(C10>0,D10/C10,0)
B11: Entertainment | C11: 150 | D11: 125 | E11: =C11-D11 | F11: =IF(C11>0,D11/C11,0)
B12: Personal Care | C12: 100 | D12: 95 | E12: =C12-D12 | F12: =IF(C12>0,D12/C12,0)
B13: Gifts | C13: 100 | D13: 150 | E13: =C13-D13 | F13: =IF(C13>0,D13/C13,0)
B14: Miscellaneous | C14: 200 | D14: 180 | E14: =C14-D14 | F14: =IF(C14>0,D14/C14,0)
E15: =C15-D15 | F15: =IF(C15>0,D15/C15,0)
E16: =C16-D16 | F16: =IF(C16>0,D16/C16,0)
E17: =C17-D17 | F17: =IF(C17>0,D17/C17,0)
E18: =C18-D18 | F18: =IF(C18>0,D18/C18,0)
E19: =C19-D19 | F19: =IF(C19>0,D19/C19,0)
B21: TOTAL | C21: =SUM(C7:C19) | D21: =SUM(D7:D19) | E21: =C21-D21
E25: =D21

Sheet Settings
B2: Settings & Assumptions
A5: Emergency Fund Balance | B5: 15000
A6: Target Savings Rate | B6: 0.2
A7: Expected Income Growth | B7: 0.03
A8: Expected Expense Growth | B8: 0.025
