Workbook

Sheet Instructions
B2: 📊 Net Worth Dashboard
B4: Welcome to your premium financial planning tool from Charge Wealth!
B6: 🎯 Overview
B7: • Track your complete financial picture with assets, liabilities, and net worth over time.
B8: • Set goals and watch your progress with visual charts and trend analysis.
B9: • Update monthly for best results.
B11: 📝 Getting Started
B12: • Enter all assets in the 'Assets' sheet (cash, investments, property, etc.)
B13: • Enter all liabilities in the 'Liabilities' sheet (mortgages, loans, credit cards)
B14: • The Dashboard calculates your net worth automatically
B15: • Use 'History' to track changes over time
B17: 💡 Pro Tips
... B29: Questions? Visit chargewealth.co for support and more premium tools.

Sheet Dashboard
B2: Net Worth Dashboard
B3: Your Complete Financial Picture
B4: Powered by Charge Wealth
B6: NET WORTH SUMMARY
B8: Total Assets | C8: =Assets!I40
B9: Total Liabilities | C9: =Liabilities!I35
B10: NET WORTH | C10: =C8-C9
B13: ASSET ALLOCATION
B15: Cash & Equivalents | C15: =Assets!I10 | D15: =IF($C$8>0,C15/$C$8,0)
B16: Investments | C16: =Assets!I20 | D16: =IF($C$8>0,C16/$C$8,0)
B17: Retirement Accounts | C17: =Assets!I28 | D17: =IF($C$8>0,C17/$C$8,0)
B18: Real Estate | C18: =Assets!I33 | D18: =IF($C$8>0,C18/$C$8,0)
B19: Other Assets | C19: =Assets!I38 | D19: =IF($C$8>0,C19/$C$8,0)
B22: NET WORTH GOALS
B24: Goal | C24: Target | D24: Current | E24: Progress
B25: 1-Year Goal | C25: 150000 | D25: =$C$10 | E25: =MIN(1,D25/C25)
B26: 5-Year Goal | C26: 500000 | D26: =$C$10 | E26: =MIN(1,D26/C26)
B27: 10-Year Goal | C27: 1500000 | D27: =$C$10 | E27: =MIN(1,D27/C27)
B28: Financial Independence | C28: 2000000 | D28: =$C$10 | E28: =MIN(1,D28/C28)

Sheet Assets
B2: Asset Tracker
B3: Everything You Own
B4: Powered by Charge Wealth
B6: CASH & EQUIVALENTS
B7: Account | C7: Institution | D7: Balance | E7: Notes
B8: Checking Account | C8: Chase | D8: 8500
B9: Savings Account | C9: Marcus | D9: 25000
B10: Money Market | C10: Fidelity | D10: 15000 | I10: =D15
B11: Emergency Fund | C11: Ally | D11: 30000
B15: Cash Subtotal | D15: =SUM(D8:D14)
B17: INVESTMENTS (Taxable)
B18: Account | C18: Institution | D18: Balance | E18: Notes
B19: Brokerage Account | C19: Fidelity | D19: 85000
B20: Stock Holdings | C20: TD Ameritrade | D20: 25000 | I20: =D25
B21: Index Funds | C21: Vanguard | D21: 50000
B25: Investment Subtotal | D25: =SUM(D19:D24)
B27: RETIREMENT ACCOUNTS
B28: Account | C28: Institution | D28: Balance | E28: Notes | I28: =D33
B29: 401(k) | C29: Employer Plan | D29: 125000
B30: Roth IRA | C30: Vanguard | D30: 45000
B31: Traditional IRA | C31: Fidelity | D31: 30000
B32: HSA | C32: HealthEquity | D32: 8000
B33: Retirement Subtotal | D33: =SUM(D29:D32) | I33: =D38
B35: REAL ESTATE
B36: Primary Residence | D36: 450000
B37: Rental Property | D37: 0
B38: Real Estate Subtotal | D38: =SUM(D36:D37) | I38: =D43
B40: OTHER ASSETS | I40: =D45
B41: Vehicles | D41: 28000
B42: Other (Jewelry, Collectibles) | D42: 5000
B43: Other Subtotal | D43: =SUM(D41:D42)
B45: TOTAL ASSETS | D45: =I10+I20+I28+I33+I38

Sheet Liabilities
B2: Liability Tracker
B3: Everything You Owe
B4: Powered by Charge Wealth
B6: MORTGAGE
B7: Property | C7: Lender | D7: Balance | E7: Rate | F7: Payment
B8: Primary Residence | C8: Wells Fargo | D8: 320000 | E8: 0.0625 | F8: 2100
B10: AUTO LOANS
B11: Vehicle | C11: Lender | D11: Balance | E11: Rate | F11: Payment
B14: Auto Subtotal | D14: =SUM(D12:D13)
B16: STUDENT LOANS
B17: Loan | C17: Servicer | D17: Balance | E17: Rate | F17: Payment
B18: Federal Loans | C18: Nelnet | D18: 25000 | E18: 0.055 | F18: 280
B21: Student Loan Subtotal | D21: =SUM(D18:D20)
B23: CREDIT CARDS
B24: Card | C24: Issuer | D24: Balance | E24: Rate | F24: Limit
B28: Credit Card Subtotal | D28: =SUM(D25:D27)
B30: TOTAL LIABILITIES | D30: =D8+D14+D21+D28
I35: =D30

Sheet History
B2: Net Worth History
B3: Track Your Progress Over Time
B4: Powered by Charge Wealth
B6: Date | C6: Assets | D6: Liabilities | E6: Net Worth | F6: Change | G6: % Change
B7: Jan 2024 | C7: 420000 | D7: 365000 | E7: =C7-D7 | F7: 0 | G7: 0
B8: Feb 2024 | C8: 428000 | D8: 362000 | E8: =C8-D8 | F8: =E8-E7 | G8: =IF(E7<>0,F8/E7,0)
B9: Mar 2024 | C9: 435000 | D9: 359000 | E9: =C9-D9 | F9: =E9-E8 | G9: =IF(E8<>0,F9/E8,0)
B10: Apr 2024 | C10: 442000 | D10: 356000 | E10: =C10-D10 | F10: =E10-E9 | G10: =IF(E9<>0,F10/E9,0)
B11: May 2024 | C11: 450000 | D11: 352000 | E11: =C11-D11 | F11: =E11-E10 | G11: =IF(E10<>0,F11/E10,0)
B12: Jun 2024 | C12: 460000 | D12: 348000 | E12: =C12-D12 | F12: =E12-E11 | G12: =IF(E11<>0,F12/E11,0)
E13: =IF(C13="","",C13-D13) | F13: =IF(E13="","",E13-E12) | G13: =IF(OR(E13="",E12=0),"",F13/E12)
E14: =IF(C14="","",C14-D14) | F14: =IF(E14="","",E14-E13) | G14: =IF(OR(E14="",E13=0),"",F14/E13)
E15: =IF(C15="","",C15-D15) | F15: =IF(E15="","",E15-E14) | G15: =IF(OR(E15="",E14=0),"",F15/E14)
E16: =IF(C16="","",C16-D16) | F16: =IF(E16="","",E16-E15) | G16: =IF(OR(E16="",E15=0),"",F16/E15)
E17: =IF(C17="","",C17-D17) | F17: =IF(E17="","",E17-E16) | G17: =IF(OR(E17="",E16=0),"",F17/E16)
E18: =IF(C18="","",C18-D18) | F18: =IF(E18="","",E18-E17) | G18: =IF(OR(E18="",E17=0),"",F18/E17)
E19: =IF(C19="","",C19-D19) | F19: =IF(E19="","",E19-E18) | G19: =IF(OR(E19="",E18=0),"",F19/E18)
E20: =IF(C20="","",C20-D20) | F20: =IF(E20="","",E20-E19) | G20: =IF(OR(E20="",E19=0),"",F20/E19)
E21: =IF(C21="","",C21-D21) | F21: =IF(E21="","",E21-E20) | G21: =IF(OR(E21="",E20=0),"",F21/E20)
E22: =IF(C22="","",C22-D22) | F22: =IF(E22="","",E22-E21) | G22: =IF(OR(E22="",E21=0),"",F22/E21)
E23: =IF(C23="","",C23-D23) | F23: =IF(E23="","",E23-E22) | G23: =IF(OR(E23="",E22=0),"",F23/E22)
E24: =IF(C24="","",C24-D24) | F24: =IF(E24="","",E24-E23) | G24: =IF(OR(E24="",E23=0),"",F24/E23)
